example_rtl/counter.v
// Simple 8-bit counter with synchronous reset
module counter (
    input  wire clk,
    input  wire rst,
    input  wire en,
    output reg  [7:0] count
);
    always @(posedge clk) begin
        if (rst) begin
            count <= 8'd0;
        end else if (en) begin
            count <= count + 8'd1;
        end
    end
endmodule

temp_artifacts_2/waves/generated_default.vcd
$version Generated by VerilatedVcd $end
$timescale 1ps $end
 $scope module TOP $end
  $var wire 1 # clk $end
  $var wire 1 $ rst $end
  $var wire 1 % en $end
  $var wire 8 & count [7:0] $end
  $scope module counter $end
   $var wire 1 # clk $end
   $var wire 1 $ rst $end
   $var wire 1 % en $end
   $var wire 8 & count [7:0] $end
  $upscope $end
 $upscope $end
$enddefinitions $end


#0
0#
0$
0%
b00000000 &
#2
1#
#3
0#
#4
1#
#5
0#
#6
1#
#7
0#
#8
1#
#9
0#
#10
1#
#11
0#
#12
1#
#13
0#
#14
1#
#15
0#
#16
1#
#17
0#
1%
#18
1#
b00000001 &
#19
0#
#20
1#
b00000010 &
#21
0#
#22
1#
b00000011 &
#23
0#
#24
1#
b00000100 &
#25
0#
#26
1#
b00000101 &
#27
0#
#28
1#
b00000110 &
#29
0#
#30
1#
b00000111 &
#31
0#
#32
1#
b00001000 &
#33
0#
#34
1#
b00001001 &
#35
0#
#36
1#
b00001010 &
